docstring_to_markdown/__init__.py
docstring_to_markdown/_utils.py
docstring_to_markdown/cpython.py
docstring_to_markdown/google.py
docstring_to_markdown/plain.py
docstring_to_markdown/py.typed
docstring_to_markdown/rst.py
docstring_to_markdown/types.py
docstring_to_markdown-0.16.dist-info/LICENSE
docstring_to_markdown-0.16.dist-info/METADATA
docstring_to_markdown-0.16.dist-info/WHEEL
docstring_to_markdown-0.16.dist-info/entry_points.txt
docstring_to_markdown-0.16.dist-info/top_level.txt
docstring_to_markdown-0.16.dist-info/RECORD
