Metadata-Version: 2.1
Name: docstring-to-markdown
Version: 0.16
Summary: On the fly conversion of Python docstrings to markdown
Author: Michał Krassowski
Author-email: krassowski.michal+pypi@gmail.com
License: LGPL-2.1-or-later
Project-URL: Bug Tracker, https://github.com/python-lsp/docstring-to-markdown/issues
Project-URL: Source Code, https://github.com/python-lsp/docstring-to-markdown
Keywords: Docstring,conversion,markdown
Classifier: Intended Audience :: Developers
Classifier: License :: OSI Approved :: GNU Lesser General Public License v2 or later (LGPLv2+)
Classifier: Programming Language :: Python
Classifier: Topic :: Text Processing :: Markup
Classifier: Topic :: Documentation :: Sphinx
Requires-Python: >=3.7
License-File: LICENSE
Requires-Dist: importlib-metadata>=3.6
Requires-Dist: typing_extensions>=4.6
